README.md
pyproject.toml
setup.py
contract/__init__.py
contract/semantic_lambda.py
models/__init__.py
models/models.py
session/__init__.py
session/session_mgr.py
test_wrapper.egg-info/PKG-INFO
test_wrapper.egg-info/SOURCES.txt
test_wrapper.egg-info/dependency_links.txt
test_wrapper.egg-info/requires.txt
test_wrapper.egg-info/top_level.txt
utilities/__init__.py
utilities/toml.py
wrapper/__init__.py
wrapper/main.py
wrapper/wrapper.py