Metadata-Version: 2.1
Name: test_wrapper
Version: 0.1
Requires-Dist: annotated-types==0.6.0
Requires-Dist: anyio==3.7.1
Requires-Dist: certifi==2023.11.17
Requires-Dist: charset-normalizer==3.3.2
Requires-Dist: click==8.1.7
Requires-Dist: docutils==0.20.1
Requires-Dist: exceptiongroup==1.2.0
Requires-Dist: fastapi==0.104.1
Requires-Dist: h11==0.14.0
Requires-Dist: idna==3.6
Requires-Dist: importlib-metadata==7.0.1
Requires-Dist: jaraco.classes==3.3.0
Requires-Dist: keyring==24.3.0
Requires-Dist: markdown-it-py==3.0.0
Requires-Dist: mdurl==0.1.2
Requires-Dist: more-itertools==10.2.0
Requires-Dist: nh3==0.2.15
Requires-Dist: pkginfo==1.9.6
Requires-Dist: pydantic==2.5.2
Requires-Dist: pydantic_core==2.14.5
Requires-Dist: Pygments==2.17.2
Requires-Dist: readme-renderer==42.0
Requires-Dist: requests==2.31.0
Requires-Dist: requests-toolbelt==1.0.0
Requires-Dist: rfc3986==2.0.0
Requires-Dist: rich==13.7.0
Requires-Dist: sdist==0.0.0
Requires-Dist: sniffio==1.3.0
Requires-Dist: starlette==0.27.0
Requires-Dist: toml==0.10.2
Requires-Dist: twine==4.0.2
Requires-Dist: typing_extensions==4.8.0
Requires-Dist: urllib3==2.1.0
Requires-Dist: uvicorn==0.24.0.post1
Requires-Dist: zipp==3.17.0
